lakaodi/__init__.py
lakaodi/send_notification_telegram.py
lakaodi-0.2.dist-info/METADATA
lakaodi-0.2.dist-info/WHEEL
lakaodi-0.2.dist-info/entry_points.txt
lakaodi-0.2.dist-info/top_level.txt
lakaodi-0.2.dist-info/RECORD
